Metadata-Version: 2.4
Name: profile-translator-blocklist
Version: 0.11.0
Summary: Translate IoT YAML profiles to NFTables / NFQueue files for a block-list firewall.
Author-email: François De Keersmaeker <francois.dekeersmaeker+github@proton.me>
Maintainer-email: François De Keersmaeker <francois.dekeersmaeker+github@proton.me>
License-Expression: GPL-3.0-or-later
Project-URL: Homepage, https://github.com/smart-home-network-security/profile-translator-blocklist
Project-URL: Source, https://github.com/smart-home-network-security/profile-translator-blocklist
Keywords: yaml,firewall,nftables,nfqueue
Classifier: Development Status :: 3 - Alpha
Classifier: Programming Language :: Python :: 3
Classifier: Programming Language :: Python :: 3.8
Classifier: Programming Language :: Python :: 3.9
Classifier: Programming Language :: Python :: 3.10
Classifier: Programming Language :: Python :: 3.11
Classifier: Programming Language :: Python :: 3.12
Classifier: Programming Language :: Python :: 3 :: Only
Classifier: Operating System :: OS Independent
Requires-Python: >=3.8
License-File: LICENSE
Requires-Dist: PyYAML
Requires-Dist: Jinja2
Requires-Dist: pyyaml-loaders
Dynamic: license-file
